trexit/__init__.py
trexit/cli.py
trexit/content_writer.py
trexit/tree_printer.py
trexit-0.2.1.dist-info/METADATA
trexit-0.2.1.dist-info/WHEEL
trexit-0.2.1.dist-info/entry_points.txt
trexit-0.2.1.dist-info/RECORD
